hakilo/__init__.py
hakilo/hakilo.py
hakilo/hakilo_sentence.py
hakilo/split_sentence.py
hakilo-1.1.1.dist-info/LICENSE
hakilo-1.1.1.dist-info/METADATA
hakilo-1.1.1.dist-info/WHEEL
hakilo-1.1.1.dist-info/top_level.txt
hakilo-1.1.1.dist-info/RECORD
