Metadata-Version: 2.1
Name: hakilo
Version: 1.1.1
Summary: A tool for splitting a text into sentences.
Home-page: https://github.com/Indrikoterio/hakilo-python
Author: Cleve (Klivo) Lendon
Author-email: indriko@yahoo.com
License: UNKNOWN
Platform: UNKNOWN
Classifier: Programming Language :: Python :: 3
Classifier: License :: Public Domain
Classifier: Operating System :: OS Independent
Requires-Python: >=3.5
